nwb_models-0.2.0.dist-info/METADATA
nwb_models-0.2.0.dist-info/WHEEL
nwb_models/__init__.py
nwb_models/models/.DS_Store
nwb_models/models/__init__.py
nwb_models/models/pydantic/__init__.py
nwb_models/models/pydantic/core/__init__.py
nwb_models/models/pydantic/core/v2_2_0/__init__.py
nwb_models/models/pydantic/core/v2_2_0/core_nwb_base.py
nwb_models/models/pydantic/core/v2_2_0/core_nwb_behavior.py
nwb_models/models/pydantic/core/v2_2_0/core_nwb_device.py
nwb_models/models/pydantic/core/v2_2_0/core_nwb_ecephys.py
nwb_models/models/pydantic/core/v2_2_0/core_nwb_epoch.py
nwb_models/models/pydantic/core/v2_2_0/core_nwb_file.py
nwb_models/models/pydantic/core/v2_2_0/core_nwb_icephys.py
nwb_models/models/pydantic/core/v2_2_0/core_nwb_image.py
nwb_models/models/pydantic/core/v2_2_0/core_nwb_misc.py
nwb_models/models/pydantic/core/v2_2_0/core_nwb_ogen.py
nwb_models/models/pydantic/core/v2_2_0/core_nwb_ophys.py
nwb_models/models/pydantic/core/v2_2_0/core_nwb_retinotopy.py
nwb_models/models/pydantic/core/v2_2_0/namespace.py
nwb_models/models/pydantic/core/v2_2_1/__init__.py
nwb_models/models/pydantic/core/v2_2_1/core_nwb_base.py
nwb_models/models/pydantic/core/v2_2_1/core_nwb_behavior.py
nwb_models/models/pydantic/core/v2_2_1/core_nwb_device.py
nwb_models/models/pydantic/core/v2_2_1/core_nwb_ecephys.py
nwb_models/models/pydantic/core/v2_2_1/core_nwb_epoch.py
nwb_models/models/pydantic/core/v2_2_1/core_nwb_file.py
nwb_models/models/pydantic/core/v2_2_1/core_nwb_icephys.py
nwb_models/models/pydantic/core/v2_2_1/core_nwb_image.py
nwb_models/models/pydantic/core/v2_2_1/core_nwb_misc.py
nwb_models/models/pydantic/core/v2_2_1/core_nwb_ogen.py
nwb_models/models/pydantic/core/v2_2_1/core_nwb_ophys.py
nwb_models/models/pydantic/core/v2_2_1/core_nwb_retinotopy.py
nwb_models/models/pydantic/core/v2_2_1/namespace.py
nwb_models/models/pydantic/core/v2_2_2/__init__.py
nwb_models/models/pydantic/core/v2_2_2/core_nwb_base.py
nwb_models/models/pydantic/core/v2_2_2/core_nwb_behavior.py
nwb_models/models/pydantic/core/v2_2_2/core_nwb_device.py
nwb_models-0.2.0.dist-info/RECORD
