Metadata-Version: 2.1
Name: nwb-models
Version: 0.2.0
Summary: Pydantic/LinkML models for Neurodata Without Borders
Author-Email: sneakers-the-rat <sneakers-the-rat@protonmail.com>
License: AGPL-3.0
Requires-Python: >=3.10
Requires-Dist: pydantic>=2.3.0
Requires-Dist: numpydantic>=1.3.3
Requires-Dist: pandas>=2.2.2
